audiosalad_sdk/__init__.py
audiosalad_sdk/client.py
audiosalad_sdk/services/__init__.py
audiosalad_sdk/services/api.py
audiosalad_sdk/services/web.py
audiosalad_sdk/utils.py
audiosalad_python_sdk-0.0.1.dist-info/METADATA
audiosalad_python_sdk-0.0.1.dist-info/WHEEL
audiosalad_python_sdk-0.0.1.dist-info/RECORD
