Metadata-Version: 2.1
Name: audiosalad-python-sdk
Version: 0.0.1
Summary: Unofficial and open source Python library for interacting with the AudioSalad API
License: MIT
Author: Mariusz Smenżyk
Author-email: mariusz.smenzyk@musictechlab.io
Requires-Python: >=3.13,<4.0
Classifier: License :: OSI Approved :: MIT License
Classifier: Programming Language :: Python :: 3
Requires-Dist: requests (>=2.32.3,<3.0.0)
